aws_iam_generator/__init__.py
aws_iam_generator/account.py
aws_iam_generator/aws.py
aws_iam_generator/generator.py
aws_iam_generator/policy.py
aws_iam_generator/role.py
aws_iam_generator/serializers.py
aws_iam_generator/utils.py
aws_iam_generator/validators.py
tests/__init__.py
tests/conftest.py
tests/test_serialization.py
tests/example1/__init__.py
tests/example1/conftest.py
tests/example1/test_example1.py
tests/example2/__init__.py
tests/example2/conftest.py
tests/example2/test_example.py
tests/example3/__init__.py
tests/example3/conftest.py
tests/example3/test_example.py
tests/example4/__init__.py
tests/example4/conftest.py
tests/example4/test_example.py
aws_iam_generator-0.9.5.dist-info/METADATA
aws_iam_generator-0.9.5.dist-info/WHEEL
aws_iam_generator-0.9.5.dist-info/top_level.txt
aws_iam_generator-0.9.5.dist-info/RECORD
