Metadata-Version: 2.1
Name: aws-iam-generator
Version: 0.9.5
Summary: Utilities package for pynamodb.
Home-page: https://github.com/micmurawski/aws-iam-generator
Author: Michal Murawski
Author-email: mmurawski777@gmail.com
License: MIT
Platform: UNKNOWN
Classifier: License :: OSI Approved :: MIT License
Classifier: Programming Language :: Python :: 3
Classifier: Programming Language :: Python :: 3.6
Classifier: Programming Language :: Python :: 3.7
Classifier: Programming Language :: Python :: 3.8
Requires-Python: >=3.6
Requires-Dist: marshmallow (<4.0.0,>=3.3.0)
Requires-Dist: troposphere (>=2.6.3<3.0.0)
Requires-Dist: PyYAML (<6.0.0,>=5.3)
